LICENSE
README.md
nb_pdf_template/__init__.py
nb_pdf_template/jupyter_python.py
nb_pdf_template-5.0.1.data/data/share/jupyter/nbconvert/templates/latex_authentic/conf.json
nb_pdf_template-5.0.1.data/data/share/jupyter/nbconvert/templates/latex_authentic/index.tex.j2
nb_pdf_template-5.0.1.data/data/share/jupyter/nbconvert/templates/latex_authentic/index_A4.tex.j2
nb_pdf_template-5.0.1.data/data/share/jupyter/nbconvert/templates/latex_authentic/m.tex.j2
nb_pdf_template-5.0.1.data/data/share/jupyter/nbconvert/templates/latex_authentic/m_A4.tex.j2
nb_pdf_template-5.0.1.dist-info/METADATA
nb_pdf_template-5.0.1.dist-info/WHEEL
nb_pdf_template-5.0.1.dist-info/entry_points.txt
nb_pdf_template-5.0.1.dist-info/licenses/LICENSE
nb_pdf_template-5.0.1.dist-info/RECORD
