Metadata-Version: 2.4
Name: nb_pdf_template
Version: 5.0.1
Summary: LaTeX templates for Jupyter notebook conversion to PDF
Project-URL: Homepage, https://github.com/t-makaro/nb_pdf_template
Author: Tyler Makaro
License: MIT
License-File: LICENSE
Classifier: Development Status :: 5 - Production/Stable
Classifier: License :: OSI Approved :: MIT License
Classifier: Programming Language :: Python :: 3
Classifier: Topic :: Text Processing :: Markup :: LaTeX
Requires-Python: >=3.6
